web3mt/__init__.py
web3mt/cex/__init__.py
web3mt/cex/base.py
web3mt/cex/bybit/__init__.py
web3mt/cex/bybit/bybit.py
web3mt/cex/bybit/models.py
web3mt/cex/models.py
web3mt/cex/okx/__init__.py
web3mt/cex/okx/models.py
web3mt/cex/okx/okx.py
web3mt/consts.py
web3mt/dex/__init__.py
web3mt/dex/bridges/__init__.py
web3mt/dex/bridges/abi.json
web3mt/dex/bridges/base.py
web3mt/dex/bridges/bungee.py
web3mt/dex/bridges/relay.py
web3mt/dex/bridges/routernitro.py
web3mt/dex/models.py
web3mt/dex/uniswap/__init__.py
web3mt/dex/uniswap/abi.json
web3mt/dex/uniswap/uniswap.py
web3mt/local_db/__init__.py
web3mt/local_db/core.py
web3mt/models.py
web3mt/offchain/__init__.py
web3mt/offchain/coingecko/__init__.py
web3mt/offchain/coingecko/coingecko.py
web3mt/offchain/coingecko/coins.json
web3mt/onchain/__init__.py
web3mt/onchain/aptos/__init__.py
web3mt/onchain/aptos/bluemove.py
web3mt/onchain/aptos/client.py
web3mt/onchain/aptos/models.py
web3mt/onchain/aptos/queries/graphql.config.yml
web3mt/onchain/aptos/queries/nfts_data.graphql
web3mt/onchain/aptos/queries/tokens_data.graphql
web3mt/onchain/evm/__init__.py
web3mt/onchain/evm/client.py
web3mt/onchain/evm/models.py
web3mt/utils/__init__.py
web3mt/utils/custom_sessions.py
web3mt/utils/file_manager.py
web3mt/utils/format_number.py
web3mt/utils/imap.py
web3mt/utils/logger.py
web3mt/utils/sleeping.py
web3mt/utils/webshare.py
web3mt/utils/windows.py
web3mt-0.1.3.dist-info/METADATA
web3mt-0.1.3.dist-info/WHEEL
web3mt-0.1.3.dist-info/RECORD
